{
 "add_total_row": 0,
 "add_translate_data": 0,
 "columns": [],
 "creation": "2025-12-27 17:50:31.455742",
 "disabled": 0,
 "docstatus": 0,
 "doctype": "Report",
 "filters": [],
 "idx": 0,
 "is_standard": "Yes",
 "letter_head": null,
 "modified": "2025-12-27 17:50:31.455742",
 "modified_by": "Administrator",
 "module": "CashFree Integration",
 "name": "Payout Dashboard",
 "owner": "Administrator",
 "prepared_report": 0,
 "ref_doctype": "Cashfree Payout Log",
 "report_name": "Payout Dashboard",
 "report_type": "Script Report",
 "roles": [],
 "timeout": 0
}